taskflow/__init__.py
taskflow/__main__.py
taskflow/config.py
taskflow_desktop-0.1.0.dist-info/licenses/LICENSE
taskflow_desktop-0.1.0.dist-info/METADATA
taskflow_desktop-0.1.0.dist-info/WHEEL
taskflow_desktop-0.1.0.dist-info/top_level.txt
taskflow_desktop-0.1.0.dist-info/RECORD
