Metadata-Version: 2.4
Name: taskflow-desktop
Version: 0.1.0
Summary: A comprehensive task management application
Author-email: Erton Miranda <erton.miranda@quatto.com.br>
License: MIT
Requires-Python: >=3.8
License-File: LICENSE
Requires-Dist: PyQt6>=6.4.0
Requires-Dist: SQLAlchemy>=2.0.0
Requires-Dist: pydantic>=2.0.0
Requires-Dist: cryptography>=39.0.0
Requires-Dist: click>=8.1.0
Requires-Dist: python-jose>=3.3.0
Requires-Dist: passlib>=1.7.4
Requires-Dist: PyYAML>=6.0
Requires-Dist: psutil>=5.9.0
Requires-Dist: prometheus-client>=0.16.0
Provides-Extra: dev
Requires-Dist: pytest>=7.3.0; extra == "dev"
Requires-Dist: pytest-cov>=4.0.0; extra == "dev"
Requires-Dist: mypy>=1.3.0; extra == "dev"
Requires-Dist: black>=23.3.0; extra == "dev"
Requires-Dist: isort>=5.12.0; extra == "dev"
Requires-Dist: flake8>=6.0.0; extra == "dev"
Requires-Dist: pylint>=2.17.0; extra == "dev"
Requires-Dist: bandit>=1.7.0; extra == "dev"
Requires-Dist: safety>=2.3.0; extra == "dev"
Dynamic: license-file
